{
    "type": "object",
    "properties": {
        "blogId": {
            "required": true,
            "type": "string"
        },
        "maxComments": {
            "type": "integer"
        },
        "postId": {
            "required": true,
            "type": "string"
        },
        "userId": {
            "required": true,
            "type": "string"
        },
        "prettyPrint": {
            "type": "boolean",
            "default": true
        },
        "quotaUser": {
            "type": "string"
        },
        "userIp": {
            "type": "string"
        }
    }
}